sqlrooms/server/__init__.py
sqlrooms/server/__main__.py
sqlrooms/server/auth.py
sqlrooms/server/db_async.py
sqlrooms/server/query.py
sqlrooms/server/server.py
sqlrooms/server/crdt/__init__.py
sqlrooms/server/crdt/state.py
sqlrooms/server/crdt/ws.py
sqlrooms/server/tests/__init__.py
sqlrooms/server/tests/test_auth.py
sqlrooms/server/tests/test_concurrency.py
sqlrooms/server/tests/test_meta_storage.py
sqlrooms/server/tests/test_query.py
sqlrooms/server/tests/test_websocket.py
sqlrooms_server-0.1.0.dist-info/METADATA
sqlrooms_server-0.1.0.dist-info/WHEEL
sqlrooms_server-0.1.0.dist-info/entry_points.txt
sqlrooms_server-0.1.0.dist-info/licenses/LICENSE
sqlrooms_server-0.1.0.dist-info/RECORD
