Metadata-Version: 2.4
Name: sqlrooms-server
Version: 0.1.0
Summary: SQLRooms DuckDB websocket server runtime
Project-URL: homepage, https://sqlrooms.com
Project-URL: repository, https://github.com/sqlrooms/sqlrooms
Author: SQLRooms Contributors
License-Expression: MIT
License-File: LICENSE
Classifier: License :: OSI Approved :: MIT License
Classifier: Programming Language :: Python :: 3
Classifier: Programming Language :: Python :: 3.10
Classifier: Programming Language :: Python :: 3.11
Classifier: Programming Language :: Python :: 3.12
Requires-Python: >=3.10
Requires-Dist: diskcache
Requires-Dist: duckdb<1.5.0,>=1.4.0
Requires-Dist: loro>=1.10.0
Requires-Dist: pandas
Requires-Dist: pyarrow
Requires-Dist: socketify
Requires-Dist: ujson
